backup/__init__.py
backup/__main__.py
backupworkspace-0.2.1.dist-info/METADATA
backupworkspace-0.2.1.dist-info/WHEEL
backupworkspace-0.2.1.dist-info/entry_points.txt
backupworkspace-0.2.1.dist-info/top_level.txt
backupworkspace-0.2.1.dist-info/RECORD
