Metadata-Version: 2.4
Name: backupworkspace
Version: 0.2.1
Summary: Quickly back up your workspace.
Home-page: https://github.com/xystudio889/backupworkspace
Author: xystudio
Author-email: xystudio <173288240@qq.com>
Keywords: backup,git,workspace,snapshot
Classifier: Programming Language :: Python :: 3
Classifier: License :: OSI Approved :: MIT License
Classifier: Operating System :: OS Independent
Requires-Python: >=3.8
Provides-Extra: dev
Dynamic: author
Dynamic: home-page
Dynamic: requires-python
